gensarpy/__init__.py
gensarpy/convergence_tests.py
gensarpy-0.1.2.dist-info/LICENSE
gensarpy-0.1.2.dist-info/METADATA
gensarpy-0.1.2.dist-info/WHEEL
gensarpy-0.1.2.dist-info/top_level.txt
gensarpy-0.1.2.dist-info/RECORD
