Metadata-Version: 2.1
Name: gensarpy
Version: 0.1.2
Summary: A Python library for testing the convergence of mathematical series.
Home-page: https://github.com/your_username/gensarpy
Author: Gencer
Author-email: gencersarpmert3@gmail.com
Classifier: Programming Language :: Python :: 3
Classifier: License :: OSI Approved :: MIT License
Classifier: Operating System :: OS Independent
Requires-Python: >=3.6
License-File: LICENSE
Requires-Dist: sympy
